suntm/__init__.py
suntm/base.py
suntm/snmf.py
suntm/suntopic.py
suntm/test_nb.ipynb
suntm/utils.py
suntm-0.0.3.dist-info/METADATA
suntm-0.0.3.dist-info/WHEEL
suntm-0.0.3.dist-info/licenses/LICENSE
suntm-0.0.3.dist-info/RECORD
